odoo/addons/web_widget_mermaid/README.rst
odoo/addons/web_widget_mermaid/__init__.py
odoo/addons/web_widget_mermaid/__manifest__.py
odoo/addons/web_widget_mermaid/demo/res_users_flowchart.xml
odoo/addons/web_widget_mermaid/i18n/ca.po
odoo/addons/web_widget_mermaid/i18n/es.po
odoo/addons/web_widget_mermaid/i18n/fr.po
odoo/addons/web_widget_mermaid/i18n/pt_BR.po
odoo/addons/web_widget_mermaid/i18n/web_widget_mermaid.pot
odoo/addons/web_widget_mermaid/readme/CONTRIBUTORS.rst
odoo/addons/web_widget_mermaid/readme/DESCRIPTION.rst
odoo/addons/web_widget_mermaid/readme/USAGE.rst
odoo/addons/web_widget_mermaid/static/description/flowchart_example.png
odoo/addons/web_widget_mermaid/static/description/icon.png
odoo/addons/web_widget_mermaid/static/description/index.html
odoo/addons/web_widget_mermaid/static/lib/mermaid/mermaid.js
odoo/addons/web_widget_mermaid/static/src/js/web_widget_mermaid.js
odoo/addons/web_widget_mermaid/static/src/scss/web_widget_mermaid_default_theme.scss
odoo/addons/web_widget_mermaid/view/web_widget_mermaid_view.xml
odoo12_addon_web_widget_mermaid-12.0.8.4.0.99.dev15.dist-info/METADATA
odoo12_addon_web_widget_mermaid-12.0.8.4.0.99.dev15.dist-info/WHEEL
odoo12_addon_web_widget_mermaid-12.0.8.4.0.99.dev15.dist-info/top_level.txt
odoo12_addon_web_widget_mermaid-12.0.8.4.0.99.dev15.dist-info/RECORD
